FinamPy/Config.py
FinamPy/FinamPy.py
FinamPy/FinamRestPy.py
FinamPy/__init__.py
backtrader_finam/__init__.py
backtrader_finam/finam_broker.py
backtrader_finam/finam_feed.py
backtrader_finam/finam_store.py
backtrader_finam-3.0.1.dist-info/LICENSE
backtrader_finam-3.0.1.dist-info/METADATA
backtrader_finam-3.0.1.dist-info/WHEEL
backtrader_finam-3.0.1.dist-info/dependency_links.txt
backtrader_finam-3.0.1.dist-info/top_level.txt
backtrader_finam-3.0.1.dist-info/RECORD
